gauss_distribs_m/Binomialdistribution.py
gauss_distribs_m/Gaussiandistribution.py
gauss_distribs_m/Generaldistribution.py
gauss_distribs_m/__init__.py
gauss_distribs_m-0.1.dist-info/METADATA
gauss_distribs_m-0.1.dist-info/WHEEL
gauss_distribs_m-0.1.dist-info/top_level.txt
gauss_distribs_m-0.1.dist-info/RECORD
