Metadata-Version: 2.1
Name: gauss-distribs-m
Version: 0.1
Summary: Gaussian distributions
